env_example/__init__.py
env_example/ast_utils.py
env_example/main.py
env_example-0.3.1.dist-info/WHEEL
env_example-0.3.1.dist-info/entry_points.txt
env_example-0.3.1.dist-info/METADATA
env_example-0.3.1.dist-info/RECORD
