Metadata-Version: 2.3
Name: env-example
Version: 0.3.1
Summary: Add your description here
Author: Jochem Loedeman
Author-email: Jochem Loedeman <60843521+jochemloedeman@users.noreply.github.com>
License: MIT License
Requires-Python: >=3.14
